<text><front>
<pb n="1"/>
<pb n="2"/>
<pb n="3"/>
<lb n="3.001"/><head>VOYAGE
<lb n="3.002"/>DANS LES
<lb n="3.003"/>ESPACES.
<lb n="3.004"/><graphic/>
<lb n="3.005"/>A LONDRES.
<lb n="3.006"/><graphic/>
<lb n="3.007"/>1758.</head>
<pb n="4"/>
<pb n="5"/>
<lb n="5.001"/><graphic/>
<lb n="5.002"/><head>A
<lb n="5.003"/>MADAME
<lb n="5.004"/>LA MARQUISE DE G**.</head>
<lb n="5.005"/><p><seg rend = "caps"  type = "initials">M</seg>ADAME,</p>
<lb n="5.006"/><p>  <seg rend="italic">En</seg> <seg rend="italic">vous dédiant ce petit</seg>
<lb n="5.007"/><seg rend="italic">Ouvrage, je ne résisterois pas</seg>
<lb n="5.008"/><seg rend="italic">à l'envie de parler de la justesse</seg>
<lb n="5.009"/>{et} <seg rend="italic">du brillant de votre esprit, de</seg>
<pb n="6"/>
<lb n="6.001"/><seg rend="italic">la délicatesse de votre goût, des</seg>
<lb n="6.002"/><seg rend="italic">charmes de toute votre Person-</seg>
<lb n="6.003"/><seg rend="italic">ne,</seg> {et} <seg rend="italic">des graces si constam-</seg>
<lb n="6.004"/><seg rend="italic">ment attachées à ce que vous</seg>
<lb n="6.005"/><seg rend="italic">faites,</seg> {et} <seg rend="italic">à ce que vous dites,</seg>
<lb n="6.006"/><seg rend="italic">si je ne craignois qu'un frontis-</seg>
<lb n="6.007"/><seg rend="italic">pice trop beau, ne le fit paroître</seg>
<lb n="6.008"/><seg rend="italic">encore plus mince,</seg> {et} <seg rend="italic">trop peu</seg>
<lb n="6.009"/><seg rend="italic">digne de vous être offert.</seg></p>
<lb n="6.010"/><p>  <seg rend="italic">J'ai l'honneur d'être avec</seg>
<lb n="6.011"/><seg rend="italic">respect,</seg></p>
<lb n="6.012"/><p>  MADAME,</p>
<lb n="6.013"/>          <seg rend="italic">Votre très-humble</seg> {et} <seg rend="italic">très-</seg>
<lb n="6.014"/><seg rend="italic">              obéissant serviteur.</seg>
<pb n="7"/>
<fw>v</fw>
<lb n="7.001"/><graphic/>
<lb n="7.002"/><head><seg rend="italic">PREFACE.</seg></head>
<lb n="7.003"/><p><seg rend = "caps"  type = "initials">I</seg>L n'est rien de plus difficile
<lb n="7.004"/>à faire qu'une Préface, cepen-
<lb n="7.005"/>dant chaque brochure nouvelle est
<lb n="7.006"/>chargée de la sienne. Je ne me
<lb n="7.007"/>dispenserai donc pas d'une Loi
<lb n="7.008"/>aussi inviolablement observée;
<lb n="7.009"/>mais je n'en fais pas le fin, je ne
<lb n="7.010"/>suis pas médiocrement embarras-
<lb n="7.011"/>sé. Car enfin que le Lecteur équi-
<lb n="7.012"/>table se mette à ma place: dirai-
<lb n="7.013"/>je qu'on m'a enlevé mon Manus-
<lb n="7.014"/>crit? Cela n'est pas plus vrai de
<lb n="7.015"/>moi que de tant d'autres qui l'ont
<lb n="7.016"/>dit. Chanterai-je la gloire de ma
<lb n="7.017"/>modestie &amp; la défense honorable
<lb n="7.018"/>qu'elle a faite avant de se rendre?
<lb n="7.019"/>La modestie des Auteurs n'est pas
<lb n="7.020"/>en fort bonne odeur, &amp; le public
<lb n="7.021"/>depuis long-tems n'est plus dupe
<lb n="7.022"/>sur cet article. Et quand cela se-
<pb n="8"/>
<fw>vj <seg rend="italic">PREFACE</seg></fw>
<lb n="8.001"/>roit vrai, quel bien ou quel
<lb n="8.002"/>plaisir lui en reviendroit-il? Irai-
<lb n="8.003"/>je lui conter pour faire excu-
<lb n="8.004"/>ser mes fautes que c'est l'ouvrage
<lb n="8.005"/>de trois jours? <seg rend="italic">Le tems ne fait rien</seg>
<lb n="8.006"/><seg rend="italic">à l'affaire</seg>*: &amp; qui l'empêchera de
<lb n="8.007"/>penser que c'est un tour dont
<lb n="8.008"/>ma vanité se sert, pour vanter in-
<lb n="8.009"/>directement ma facilité. Expli-
<lb n="8.010"/>querai-je le plan, l'ordre &amp; la
<lb n="8.011"/>distribution des chapitres? Si on
<lb n="8.012"/>me lit on le verra. Ferai-je l'élo-
<lb n="8.013"/>ge de mon sujet, ce pourroit bien
<lb n="8.014"/>être le trait d'un mal avisé, &amp; il
<lb n="8.015"/>pourroit bien disposer à ce qu'on
<lb n="8.016"/>le trouvât plus mauvais. Et ce-
<lb n="8.017"/>pendant de qu'elle autre chose
<lb n="8.018"/>sont pleines toutes les Préfaces?
<lb n="8.019"/>Mais il me vient tout-à-coup une
<lb n="8.020"/>idée: si celle - ci ressemble aux
<lb n="8.021"/>autres, c'en est donc une. <seg rend="italic">J'ai</seg>
<lb n="8.022"/><seg rend="italic">fait de la prose, sans le sçavoir.</seg></p>
<lb n="8.023"/><seg rend ="footnotes"/>
<lb n="8.024"/><p>  <seg rend = "small">{5*} <seg rend="italic">Misantrope. Act.</seg> 1. <seg rend="italic">sect.</seg> 11.</seg></p></front>
<body>
<pb n="9"/>
<lb n="9.001"/><graphic/>
<lb n="9.002"/><head>VOYAGE
<lb n="9.003"/>DANS LES ESPACES.
<lb n="9.004"/><graphic/>
<lb n="9.005"/>CHAPITRE PREMIER.</head>
<lb n="9.006"/><p><seg rend = "caps"  type = "initials">L</seg>E quinze du mois.... dernier,
<lb n="9.007"/>je fus attaqué d'une si violente
<lb n="9.008"/>apoplexie que je restai près de
<lb n="9.009"/>vingt-quatre heures sans con-
<lb n="9.010"/>noissance. Qu'on demande à quelqu'un
<lb n="9.011"/>qui se soit trouvé dans un pareil état, ce
<lb n="9.012"/>que faisoit pour lors son ame, il répondra
<lb n="9.013"/>qu'elle étoit dans les espaces. C'est-là
<lb n="9.014"/>précisément que fut la mienne.</p>
<lb n="9.015"/><p>  Voici qui est intéressant, dira d'abord
<lb n="9.016"/>tout Physicien, un voyage dans ce Pays-
<lb n="9.017"/>là est l'unique moyen de décider la ques-
<lb n="9.018"/>tion du vuide &amp; du plein, mais je le
<lb n="9.019"/>préviens; il sera trompé dans son atten-
<pb n="10"/>
<fw>(2)</fw>
<lb n="10.001"/>te; je ne puis lui donner là-dessus le
<lb n="10.002"/>moindre éclaircissement, il ne me vint
<lb n="10.003"/>pas seulement l'idée d'en prendre; il n'y
<lb n="10.004"/>auroit je crois pas plus pensé que moi,
<lb n="10.005"/>s'il se fut trouvé tout-à-coup dans ces
<lb n="10.006"/>vastes &amp; effroyables solitudes. J'y errois
<lb n="10.007"/>à-peu-près comme une plume legère,
<lb n="10.008"/>livrée au caprice du souffle qui l'agite;
<lb n="10.009"/>je ne sçavois si je montois ou si je des-
<lb n="10.010"/>cendois, ni ou j'allois, ni quand je ces-
<lb n="10.011"/>sois d'aller, &amp; j'étois en proie à l'in-
<lb n="10.012"/>quiétude la plus amère, lorsqu'après
<lb n="10.013"/>quelques heures d'une situation aussi
<lb n="10.014"/>cruelle, je reconnus une Région habi-
<lb n="10.015"/>tée, &amp; vis devant moi un portail super-
<lb n="10.016"/>be, sur lequel étoit écrit en grandes let-
<lb n="10.017"/>tres d'or, Hôtel des Auteurs
<lb n="10.018"/>François.</p>
<lb n="10.019"/><p>  Je fus tout réjoüi à cette vûe: l'avan-
<lb n="10.020"/>ture s'est dénouée bien heureusement,
<lb n="10.021"/>me dis-je à moi-même, je vais voir
<lb n="10.022"/>bonne compagnie. J'entrai hardiment &amp;
<lb n="10.023"/>personne ne m'arrêta; je traversai plu-
<lb n="10.024"/>sieurs grandes cours &amp; j'arrivai enfin à
<lb n="10.025"/>un vestibule immense.</p>
<lb n="10.026"/><head><graphic/></head>
<pb n="11"/>
<fw>(3)</fw>
<lb n="11.001"/><graphic/>
<lb n="11.002"/><head>CHAPITRE SECOND
<lb n="11.003"/><seg rend="italic">Le Vestibule.</seg></head>
<lb n="11.004"/><p><seg rend = "caps"  type = "initials">I</seg>L étoit plein d'un nombre prodi-
<lb n="11.005"/>gieux de laquais. Dès qu'ils me virent
<lb n="11.006"/>paroître, ils se leverent promptement
<lb n="11.007"/>&amp; mirent leur chapeau bas. Ah! me
<lb n="11.008"/>dis-je, il y a de l'ordre dans ce monde,
<lb n="11.009"/>&amp; ils ne sont pas si souples chez les Sei-
<lb n="11.010"/>gneurs de l'autre. A qui êtes-vous, de-
<lb n="11.011"/>mandai-je d'un ton assuré à un de ceux
<lb n="11.012"/>qui se trouva le plus près de moi &amp; qui
<lb n="11.013"/>me parut avoir la meilleure façon? A
<lb n="11.014"/>peine lui eus-je fait cette question, que
<lb n="11.015"/>j'apperçus le nom de *** imprimé
<lb n="11.016"/>sur son front: je le vois, ajoutai-je,
<lb n="11.017"/>vous êtes à M. ***, donnez-m'en
<lb n="11.018"/>des nouvelles. Je suis si bien à M. ***,
<lb n="11.019"/>me répondit-il, que je suis M. ***
<lb n="11.020"/>lui-même. Il remarqua l'étonnement
<lb n="11.021"/>que me causoit sa réponse: tel est l'ar-
<lb n="11.022"/>rêt irrévocable que je subis, reprit-il
<lb n="11.023"/>tout de suite; je suis condamné à ser-
<lb n="11.024"/>vir ici, ceux à qui je me croyois, tout
<lb n="11.025"/>au moins, égal là-haut. Qui que vous
<lb n="11.026"/>soyez, mort ou vivant, car vous n'avez
<pb n="12"/>
<fw>(4)</fw>
<lb n="12.001"/>la mine ni de l'un, ni de l'autre; écou-
<lb n="12.002"/>tez ce que je vais vous apprendre, &amp; si
<lb n="12.003"/>vous n'êtes ici qu'en entrepôt, comme
<lb n="12.004"/>je le soupçonne, ne manquez pas d'en
<lb n="12.005"/>faire part aux Auteurs vivans.</p>
<lb n="12.006"/><p>  Chacun pese ici ce qu'il vaut, pas da-
<lb n="12.007"/>vantage: la brigue &amp; la faveur ne sçau-
<lb n="12.008"/>roient mettre un grain de plus dans une
<lb n="12.009"/>balance qui est tenue par la Justice la
<lb n="12.010"/>plus sévère. Tout cela est conforme à la
<lb n="12.011"/>croyance commune &amp; n'a rien de nou-
<lb n="12.012"/>veau pour vous, mais ceci le sera. Ceux
<lb n="12.013"/>dont les ouvrages doivent passer à l'im-
<lb n="12.014"/>mortalité, en reçoivent la récompense
<lb n="12.015"/>dans ce Palais, bâti des mains même de
<lb n="12.016"/>la gloire, &amp; duquel c'est ici le vestibu-
<lb n="12.017"/>le. Ils y sont enyvrés de plaisirs &amp; d'hon-
<lb n="12.018"/>neurs. Les Bossuets, les Fénelons, les
<lb n="12.019"/>Molieres, les Corneilles, les Racines,
<lb n="12.020"/>les Despréaux, les Rousseaux, les Mon-
<lb n="12.021"/>tesquieux, les Fontenelles, &amp;c. en sont
<lb n="12.022"/>les heureux possesseurs; pour nous,
<lb n="12.023"/>nous sommes à leurs ordres, ce nombre
<lb n="12.024"/>confus de gens bigarrés que vous voyez,
<lb n="12.025"/>fait partie de leur maison, &amp; leur bon-
<lb n="12.026"/>heur est si solidement établi, que leur
<lb n="12.027"/>train s'accroît tous les jours. A mesure
<lb n="12.028"/>que les Auteurs arrivent, ils sont jugés,
<lb n="12.029"/>&amp; la plûpart s'arrêtent ici, malheureu-
<pb n="13"/>
<fw>(5)</fw>
<lb n="13.001"/>sement pour nous; la foule augmente
<lb n="13.002"/>tellement, que bientôt, hélas! nous ne
<lb n="13.003"/>pourrons plus y être contenus, &amp; que
<lb n="13.004"/>nous y serons à la presse, en punition
<lb n="13.005"/>d'y avoir mis nos ouvrages.</p>
<lb n="13.006"/><p>  Cet appartement est bien vaste, lui
<lb n="13.007"/>dis-je, &amp; ce que vous craignez ne me
<lb n="13.008"/>paroit guère vraisemblable, n'allez donc
<lb n="13.009"/>pas vous faire un supplice d'une chose
<lb n="13.010"/>qui n'arrivera jamais; au contraire,
<lb n="13.011"/>ajoûtai-je, pour calmer le chagrin qui
<lb n="13.012"/>éclatoit dans toute sa personne, les nou-
<lb n="13.013"/>veaux venus vous amuseront par les
<lb n="13.014"/>nouvelles dont ils vous feront part.</p>
<lb n="13.015"/><p>  Ah! reprit-il amérement, comment
<lb n="13.016"/>me persuaderiez-vous une chose dont
<lb n="13.017"/>l'expérience me montre tous les jours
<lb n="13.018"/>le contraire. Il faut que la demangaison
<lb n="13.019"/>d'écrire soit devenue épydémique: les
<lb n="13.020"/>Auteurs ne viennent plus un à un &amp; de
<lb n="13.021"/>tems en tems, comme autrefois, ils
<lb n="13.022"/>descendent en troupe, &amp; s'ils étoient
<lb n="13.023"/>amusans, les verrions-nous dans ce lieu?
<lb n="13.024"/>Jettez les yeux sur tout ce monde,
<lb n="13.025"/>voyez le silence qui y règne &amp; l'ennui
<lb n="13.026"/>qui le consume: C'est la réparation de
<lb n="13.027"/>celui que nos ouvrages ont causé. Nous
<lb n="13.028"/>autres du siècle passé disons par fois quel-
<lb n="13.029"/>que chose, mais on ne peut arracher un
<pb n="14"/>
<fw>(6)</fw>
<lb n="14.001"/>mot à tous ces nouveaux débarqués, ils
<lb n="14.002"/>sont de plus que nous, condamnés à un
<lb n="14.003"/>baillement perpétuel. Examinez-en la
<lb n="14.004"/>troupe languissante &amp; soporifique: je
<lb n="14.005"/>les fixai en effet &amp; ils me parurent si
<lb n="14.006"/>prodigieusement ennuyés, que malgré
<lb n="14.007"/>la curiosité que tout cela excitoit en
<lb n="14.008"/>moi, je ne pus m'empêcher de bailler
<lb n="14.009"/>par sympathie.</p>
<lb n="14.010"/><p>  Après quelques efforts réïtérés que je
<lb n="14.011"/>fis, pour me défendre du sommeil con-
<lb n="14.012"/>tagieux qui alloit s'ensuivre; je repris
<lb n="14.013"/>la conversation ainsi: expliquez-moi, je
<lb n="14.014"/>vous en prie, si vous servez en commun
<lb n="14.015"/>les mêmes Maître, &amp; dans ce cas, pour-
<lb n="14.016"/>quoi cette différence de livrées? Le Pa-
<lb n="14.017"/>lais est commun, il y a des appartemens
<lb n="14.018"/>communs; mais outre cela, chaque
<lb n="14.019"/>Maître a sa maison particulière. Pour-
<lb n="14.020"/>quoi donc appartenez-vous à l'un plu-
<lb n="14.021"/>tôt qu'à l'autre? Quel ordre observe-
<lb n="14.022"/>t-on à cet égard? Cet ordre est tout
<lb n="14.023"/>simple, reprit-il, les mauvais comiques
<lb n="14.024"/>servent Moliere, les tragiques, Cor-
<lb n="14.025"/>neille ou Racine, ainsi du reste; en qua-
<lb n="14.026"/>lité de mauvais Poëte, je suis à M. Des-
<lb n="14.027"/>préaux.</p>
<lb n="14.028"/><p>  Dans cet instant on ouvrit une porte
<lb n="14.029"/>des appartemens intérieurs, &amp; l'on don-
<pb n="15"/>
<fw>(7)</fw>
<lb n="15.001"/>na une commission à mon homme qui
<lb n="15.002"/>me quitta.</p>
<lb n="15.003"/><p>  L'air humble &amp; bas que je remarquai
<lb n="15.004"/>à tous ces Auteurs laquais, me donna
<lb n="15.005"/>l'effronterie de les fixer en face &amp; de
<lb n="15.006"/>les considérer en détail; il n'étoit pas
<lb n="15.007"/>naturel que je me sentisse là plus de res-
<lb n="15.008"/>pect pour leurs personnes, que je n'en
<lb n="15.009"/>avois pour leurs ouvrages, la première
<lb n="15.010"/>découverte que je fis, fut qu'ils étoient
<lb n="15.011"/>tous étiquetés au front comme des livres,
<lb n="15.012"/>avec le titre de leurs œuvres, qui leur
<lb n="15.013"/>avoit mérité cette condamnation; &amp;
<lb n="15.014"/>que de noms &amp; de titres inconnus ne
<lb n="15.015"/>lus je point! la variété de toutes leurs
<lb n="15.016"/>couleurs, m'en avoit d'abord imposé;
<lb n="15.017"/>mais dans la revûe que j'en fis, que je
<lb n="15.018"/>les trouvai maussades! A travers les
<lb n="15.019"/>galons &amp; les dorures dont plusieurs
<lb n="15.020"/>étoient décorés, je vis dessous la
<lb n="15.021"/>poudre &amp; les vers qui les rongeoient.
<lb n="15.022"/>Ah! malheureux, dis-je, vous essuyez
<lb n="15.023"/>donc ici le même sort que vos œuvres
<lb n="15.024"/>là-haut. Que ne puis-je vous montrer à
<lb n="15.025"/>quelques Auteurs de ma connoissance.
<lb n="15.026"/>Voyez leur dirois-je, &amp; tremblez.*
<lb n="15.027"/>Les uns étoient affaissés sous le poids
<lb n="15.028"/><seg rend ="footnotes"/>
<lb n="15.029"/><p>  <seg rend = "small">{5*} <seg rend="italic">Discite justitiam moniti.</seg></seg></p>
<pb n="16"/>
<fw>(8)</fw>
<lb n="16.001"/>de leurs corps, tandis que d'autres mai-
<lb n="16.002"/>gres &amp; décharnés sembloient ne pas pe-
<lb n="16.003"/>ser sur leur baze. Ces gens-là, me di-
<lb n="16.004"/>sois-je, ne sont sûrement pas nourris à
<lb n="16.005"/>la même table: mais tout cela n'est pas
<lb n="16.006"/>sans cause, instruisons - nous de tout.
<lb n="16.007"/>Je cherchai long-tems avant de trouver
<lb n="16.008"/>quelqu'un de connu. Je rencontrai enfin
<lb n="16.009"/>Pradon &amp; ce fut à lui à qui je m'adres-
<lb n="16.010"/>sai.</p>
<lb n="16.011"/><p>  Puisque vos tragédies ne vous ont pas
<lb n="16.012"/>rendu maître ici, vous devez, lui dis-
<lb n="16.013"/>je, être vraisemblablement à M. Racine.
<lb n="16.014"/>Vous ne vous trompez pas, me dit-il:
<lb n="16.015"/>je vous vois ici bien des camarades, &amp;
<lb n="16.016"/>s'il faut en juger par le nombre des tra-
<lb n="16.017"/>gédies nouvelles, votre maître va deve-
<lb n="16.018"/>nir un des plus grands Seigneurs des
<lb n="16.019"/>Enfers. N'y a-t-il point de jalousse en-
<lb n="16.020"/>tre Corneille &amp; lui, ou pour éviter tout
<lb n="16.021"/>discord, y auroit-il quelque réglement
<lb n="16.022"/>entr'eux?</p>
<lb n="16.023"/><p>  Les Auteurs, me répondit il, portent
<lb n="16.024"/>leur destination en entrant ici. La force
<lb n="16.025"/>&amp; le sublime, font principalement le
<lb n="16.026"/>caractère de Corneille; ceux qui por-
<lb n="16.027"/>tent sa livrée, sont ceux qui ayant vou-
<lb n="16.028"/>lu l'imiter, s'y sont pris comme la gre-
<lb n="16.029"/>nouille auprès du bœuf. En voilà la
<pb n="17"/>
<fw>(9)</fw>
<lb n="17.001"/>bande boursouflée. Je me tournai du
<lb n="17.002"/>côté où il me les montroit, &amp; ils me
<lb n="17.003"/>semblérent tous bouffis &amp; enflés. Rien
<lb n="17.004"/>n'est si doux, continua-t-il, si tendre,
<lb n="17.005"/>si élégant que mon maître; l'air fade de
<lb n="17.006"/>ces gens risqueroit de vous donner au
<lb n="17.007"/>cœur si vous vous en approchiez de
<lb n="17.008"/>trop près: &amp; déja il me faisoit éprou-
<lb n="17.009"/>ver qu'il disoit vrai.</p>
<lb n="17.010"/><p>  Qui sont, Monsieur, ces pauvres
<lb n="17.011"/>gens si décharnés? Ce sont, me dit-il,
<lb n="17.012"/>des Auteurs dont les ouvrages sont aussi
<lb n="17.013"/>secs &amp; aussi maigres qu'eux. Et ceux-ci
<lb n="17.014"/>au contraire qui sont si bien nourris &amp;
<lb n="17.015"/>si prodigieusement grands &amp; gros? Ce
<lb n="17.016"/>sont des <seg rend="italic">in-folio,</seg> chargés de beaucoup
<lb n="17.017"/>de matière &amp; de peu d'esprit. Un Régi-
<lb n="17.018"/>ment de soldats de cette taille, me dis-
<lb n="17.019"/>je tout bas, vaudroit, tout au moins, le
<lb n="17.020"/>gain de la première bataille, comme les
<lb n="17.021"/>éléphans à Pyrhus.</p>
<lb n="17.022"/><p>  Vous me trouverez bien interrogatif,
<lb n="17.023"/>continuai-je; mais de grace expliquez-
<lb n="17.024"/>moi, si vous mangez, avec quoi on
<lb n="17.025"/>vous nourrit &amp; qui fournit à cetté dé-
<lb n="17.026"/>pense? A ces mots il prit un air austère,
<lb n="17.027"/>&amp; je vis dans ses yeux un feu qu'il n'a
<lb n="17.028"/>sûrement que dans ses ouvrages. Si nous
<lb n="17.029"/>avons jamais fait quelque chose de bon,
<pb n="18"/>
<fw>(10)</fw>
<lb n="18.001"/>dit-il, il nous vient à la bouche, nous
<lb n="18.002"/>le mâchons, le ruminons &amp; en expri-
<lb n="18.003"/>mons tout le suc; c'est-là toute notre
<lb n="18.004"/>nourriture: les alimens de la plûpart
<lb n="18.005"/>qui sont ici, se réduisent pour la suite
<lb n="18.006"/>des siécles, à quelque douzaine de vers,
<lb n="18.007"/>ou a quelques lambeaux de phrase, qui,
<lb n="18.008"/>à force d'être mâchés &amp; remâchés, n'ont
<lb n="18.009"/>presque plus pour nous aucune saveur,
<lb n="18.010"/>&amp; nous donnent un dégoût affreux; aussi
<lb n="18.011"/>sommes-nous dévorés de la faim la plus
<lb n="18.012"/>cruelle. Exhortez, Monsieur, les Au-
<lb n="18.013"/>teurs vivans, de notre part, à la souf-
<lb n="18.014"/>frir avec patience; représentez-leur for-
<lb n="18.015"/>tement qu'il vaut bien mieux pour eux
<lb n="18.016"/>qu'ils l'endurent là-haut pendant leur
<lb n="18.017"/>vie, sans écrire, que de venir l'endurer
<lb n="18.018"/>ici à jamais, pour avoir écrit.</p>
<lb n="18.019"/><p>  Tout ce que je voyois &amp; ce que je
<lb n="18.020"/>venois d'apprendre, m'inspiroit une
<lb n="18.021"/>telle horreur &amp; un tel ennui, que je
<lb n="18.022"/>commençois de partager les tourmens
<lb n="18.023"/>de ces misérables. Ne pourrois-je point,
<lb n="18.024"/>lui dis-je, entrer dans les appartemens:
<lb n="18.025"/>vous êtes bien le maître, me dit il, &amp; il
<lb n="18.026"/>m'en ouvrit tout de suite la porte.</p>
<lb n="18.027"/><head><graphic/></head>
<pb n="19"/>
<fw>(11)</fw>
<lb n="19.001"/><graphic/>
<lb n="19.002"/><head>CHAPITRE III.
<lb n="19.003"/><seg rend="italic">L'Anti-Chambre.</seg></head>
<lb n="19.004"/><p><seg rend = "caps"  type = "initials">Q</seg>Ue je me sentis soulagé! les jours
<lb n="19.005"/>en étoient bien différens. Je crus sortir
<lb n="19.006"/>de prison, en sortant de cet ennuyeux
<lb n="19.007"/>&amp; ennuyé Vestibule. Mais sur tout quel
<lb n="19.008"/>contraste dans les physionomies de ceux
<lb n="19.009"/>que j'y trouvai! les autres plates, gros-
<lb n="19.010"/>sières &amp; manquées, inspiroient le dégoût
<lb n="19.011"/>&amp; le mépris; celles-ci, gracieuses, dou-
<lb n="19.012"/>ces &amp; régulières, s'attiroient d'abord
<lb n="19.013"/>l'estime &amp; l'amitié. La politesse de leurs
<lb n="19.014"/>écrits étoit aussi dans leurs manières. Je
<lb n="19.015"/>ne tardai pas à l'éprouver. A quoi peut-
<lb n="19.016"/>on vous être utile, me dit l'un d'entre
<lb n="19.017"/>eux, d'un air prévenant, voulez-vous
<lb n="19.018"/>voir nos Maîtres? Comment vos Maî-
<lb n="19.019"/>tres, répondis-je tout ému, est-ce que
<lb n="19.020"/>vous êtes faits pour servir quelqu'un?
<lb n="19.021"/>Et nos grands Auteurs François se-
<lb n="19.022"/>roient-ils ici subalternes &amp; au service
<lb n="19.023"/>de ceux de quelque autre nation? Non,
<lb n="19.024"/>Monsieur, me repliqua M. de la Motte:
<lb n="19.025"/>car il étoit étiqueté comme on l'étoit
<lb n="19.026"/>au Vestibule, &amp; je le connus là, si je
<pb n="20"/>
<fw>(12)</fw>
<lb n="20.001"/>ne l'avois déja reconnu à sa politesse. Nos
<lb n="20.002"/>Maîtres ne le cédent à personne, leurs
<lb n="20.003"/>ouvrages seront immortels comme eux,
<lb n="20.004"/>&amp; feront constamment les délices des
<lb n="20.005"/>races futures: il n'en est pas ainsi des
<lb n="20.006"/>nôtres: ces fleurs qui ne se fanent jamais
<lb n="20.007"/>y sont trop clair semées, elles seront
<lb n="20.008"/>étouffées par les épines plus nombreuses
<lb n="20.009"/>qui y sont, &amp; entraînées dans la nuit
<lb n="20.010"/>des siècles. Ces couronnes que j'ai si
<lb n="20.011"/>souvent remportées &amp; que j'imaginois
<lb n="20.012"/>devoir toujours rester vertes, se sont
<lb n="20.013"/>séchées devant celles de Rousseau. J'ad-
<lb n="20.014"/>mire dans ces régions, où l'amour pro-
<lb n="20.015"/>pre ne nous offusque plus, les accens
<lb n="20.016"/>harmonieux de sa lyre que je mettois
<lb n="20.017"/>au-dessous de la mienne: j'étois là-haut
<lb n="20.018"/>son rival, je remplis ici le premier em-
<lb n="20.019"/>ploi de sa chambre. Heureux encore de
<lb n="20.020"/>n'avoir pas été adjugé pour mes fables
<lb n="20.021"/>à la Fontaine, chez qui l'on ne m'auroit
<lb n="20.022"/>pas fait un sort si doux.*</p>
<lb n="20.023"/><p>  Pendant qu'il me parloit ainsi, je par-
<lb n="20.024"/>courois avec des yeux avides toute sa
<lb n="20.025"/>personne, &amp; rien ne m'y paroissoit bien
<lb n="20.026"/>naturel. Ses gestes étoient affectés &amp; sa
<lb n="20.027"/><seg rend ="footnotes"/>
<lb n="20.028"/><p>  <seg rend = "small">{5*} L'on ne parle ici ni des tragédies, ni de
<lb n="20.029"/>la prose de M. de la Motte.</seg></p>
<pb n="21"/>
<fw>(13)</fw>
<lb n="21.001"/>parure comparable à celle d'une jeune
<lb n="21.002"/>coquette, l'art y éclatoit par-tout &amp; sans
<lb n="21.003"/>ménagement: Ah! me dis-je tout bas,
<lb n="21.004"/>seroit-ce la punition de celui qu'il a mis
<lb n="21.005"/>dans ses vers? &amp; les défauts de l'ou-
<lb n="21.006"/>vrage passeroient-ils par une espèce de
<lb n="21.007"/>métempsycose, dans les attitudes, les
<lb n="21.008"/>ajustemens &amp; la figure de l'Auteur? La
<lb n="21.009"/>curiosité de voir si cette idée avoit en
<lb n="21.010"/>effet quelque réalité, devint trop for-
<lb n="21.011"/>te pour y résister. Je les examinai,
<lb n="21.012"/>mais à la dérobée, dans la crainte de
<lb n="21.013"/>passer pour impoli ou de leur faire de
<lb n="21.014"/>la peine s'ils s'en appercevoient. Balzac
<lb n="21.015"/>étoit magnifique, mais son écharpe étoit
<lb n="21.016"/>trop ample, ses canons trop vastes, son
<lb n="21.017"/>collet trop empesé. Voiture étoit min-
<lb n="21.018"/>ce &amp; fluet, &amp; ne marchoit que sur la
<lb n="21.019"/>pointe des pieds. Segrais tantôt embou-
<lb n="21.020"/>choit la trompette &amp; tantôt le chalu-
<lb n="21.021"/>meau; mais le souffle lui manquoit pour
<lb n="21.022"/>l'une &amp; il faisoit de faux tons sur l'au-
<lb n="21.023"/>tre. Pavillon tenoit une posture agréa-
<lb n="21.024"/>ble &amp; naturelle, mais sans noblesse. Pe-
<lb n="21.025"/>lisson avoit beaucoup de douceur &amp;
<lb n="21.026"/>sembloit convalescent. Tout étoit com-
<lb n="21.027"/>passé &amp; symétrisé dans Bouhours. Du
<lb n="21.028"/>Cerceau avec un grand air de vivacité
<lb n="21.029"/>&amp; de gayeté, avoit peine à se soutenir
<pb n="22"/>
<fw>(14)</fw>
<lb n="22.001"/>sur ses jambes; sa ceinture étoit liée
<lb n="22.002"/>avec grace, mais sa robe étoit lâche
<lb n="22.003"/>&amp; décousue. Campistron étoit pâle &amp;
<lb n="22.004"/>débile. Chapelle &amp; la Fare, fort négli-
<lb n="22.005"/>gés, mais fort gracieux, étoient non-
<lb n="22.006"/>chalemment assis sur un sopha, &amp;c....</p>
<lb n="22.007"/><p>  Pendant que mes yeux faisoient cette
<lb n="22.008"/>échapée, j'avois cessé de faire attention
<lb n="22.009"/>à ce que me disoit M. de la Motte &amp; il
<lb n="22.010"/>s'étoit arrêté: je revins à lui. Ah! Mon-
<lb n="22.011"/>sieur, lui dis-je tout confus, ce que je
<lb n="22.012"/>vois est si nouveau pour moi, que ma
<lb n="22.013"/>distraction est bien pardonnable. Veuil-
<lb n="22.014"/>lez, je vous en conjure, reprendre le
<lb n="22.015"/>fil de votre discours. Il continua ainsi
<lb n="22.016"/>de la façon du monde la plus polie.</p>
<lb n="22.017"/><p>  Par ce que vous avez vû au Vestibu-
<lb n="22.018"/>le, vous pouvez juger de ce qui se passe
<lb n="22.019"/>ici, la différence n'est que du plus au
<lb n="22.020"/>moins. Nos alimens sont les mêmes,
<lb n="22.021"/>mais nous faisons, ajoûta-t-il d'un ton
<lb n="22.022"/>ironique, un peu meilleure chere &amp;
<lb n="22.023"/>changeons un peu plus souvent de mets.
<lb n="22.024"/>L'ennui nous gagne quelquefois à la vé-
<lb n="22.025"/>rité, mais bientôt quelque heureuse
<lb n="22.026"/>saillie nous secoue &amp; nous réveille. La
<lb n="22.027"/>foule ici n'est pas si grande &amp; nous
<lb n="22.028"/>n'avons pas la perspective affreuse d'être
<lb n="22.029"/>un jour écrasés les uns contre les autres.
<pb n="23"/>
<fw>(15)</fw>
<lb n="23.001"/>Nous aprochons de près nos Maîtres,
<lb n="23.002"/>qui sont pleins de bonté &amp; d'égards
<lb n="23.003"/>pour nous: nos emplois auprès d'eux
<lb n="23.004"/>ont mille agrémens &amp; milles charmes,
<lb n="23.005"/>en les servant dans leurs plaisirs, nous
<lb n="23.006"/>les partageons en quelque façon avec
<lb n="23.007"/>eux; c'en est toujours un bien réel que
<lb n="23.008"/>celui de les entendre.</p>
<lb n="23.009"/><p>  Je le remerciai, le mieux qu'il me
<lb n="23.010"/>fut possible, de ce qu'il venoit de m'ap-
<lb n="23.011"/>prendre. Mettez le comble à vos bon-
<lb n="23.012"/>tés, lui dis-je, permettez-moi de par-
<lb n="23.013"/>courir vos appartemens? les compli-
<lb n="23.014"/>mens sont abolis ici, sans doute; lais-
<lb n="23.015"/>sez-moi donc sans façon faire cette visi-
<lb n="23.016"/>te tout seul, je n'en verrai que mieux,
<lb n="23.017"/>parce que je ne serai point pressé par
<lb n="23.018"/>la crainte d'abuser de votre complaisan-
<lb n="23.019"/>ce. Comme il vous plaira, reprit il, je
<lb n="23.020"/>ne veux pas vous gêner.</p>
<lb n="23.021"/><p>  Je profitai sur le champ de la permis-
<lb n="23.022"/>sion qu'il me donnoit, &amp; j'employai une
<lb n="23.023"/>heure ou deux à visiter fort en détail
<lb n="23.024"/>plusieurs enfilades de chambres. Ce que
<lb n="23.025"/>j'en dirai, c'est qu'elles présentoient un
<lb n="23.026"/>coup-d'œil agréable, mais que d'ailleurs
<lb n="23.027"/>elles étoient toutes dissemblables,
<lb n="23.028"/>l'une avoit trop de jour, &amp; l'autre
<lb n="23.029"/>étoit un peu obscure. Dans celle-ci il
<pb n="24"/>
<fw>(16)</fw>
<lb n="24.001"/>y avoit tant d'ordre &amp; de symétrie,
<lb n="24.002"/>qu'on voyoit tout, d'un coup-d'œil, &amp;
<lb n="24.003"/>dans celle-là il falloit une attention ex-
<lb n="24.004"/>trême, pour démêler la confusion. Ici
<lb n="24.005"/>les tables, la cheminée, les encoignu-
<lb n="24.006"/>res étoient surchargées d'ornemens &amp;
<lb n="24.007"/>de colifichets: &amp; là, des mûrs solides
<lb n="24.008"/>&amp; régulièrement bâtis, étoient trop
<lb n="24.009"/>nus. Ici le clinquant jettoit de fausses
<lb n="24.010"/>lueurs; &amp; là, l'or éclatoit tant soit peu
<lb n="24.011"/>à travers la poussière qui l'éclipsoit. Ici
<lb n="24.012"/>les meubles à force d'être fins, n'avoient
<lb n="24.013"/>aucune consistence; &amp; là un peu trop
<lb n="24.014"/>forts, ils approchoient du grossier. Dans
<lb n="24.015"/>toutes l'on trouvoit du bon &amp; du beau,
<lb n="24.016"/>mais ils n'étoient nulle part, purs &amp;
<lb n="24.017"/>sans beaucoup d'alliage.</p>
<lb n="24.018"/><p>  Je sortis cependant assez amusé de
<lb n="24.019"/>ce que je venois de voir. M. de la Mot-
<lb n="24.020"/>te vint au-devant de moi: je le priai de
<lb n="24.021"/>vouloir bien m'introduire auprès de
<lb n="24.022"/>quelqu'un des Maîtres. M. Despréaux,
<lb n="24.023"/>me dit-il, est tout seul dans le Salon
<lb n="24.024"/>commun, donnez-vous la peine d'entrer.</p>
<lb n="24.025"/><head><graphic/></head>
<pb n="25"/>
<fw>(17)</fw>
<lb n="25.001"/><graphic/>
<lb n="25.002"/><head>CHAPITRE IV.
<lb n="25.003"/><seg rend="italic">Le Salon.</seg></head>
<lb n="25.004"/><p><seg rend = "caps"  type = "initials">J</seg>'Entrai en effet dans un Salon, le
<lb n="25.005"/>plus beau qu'on puisse imaginer. Mes
<lb n="25.006"/>yeux enchantés de la magnificence &amp;
<lb n="25.007"/>de la richesse qui y régnoient, se lais-
<lb n="25.008"/>soient entraîner à tous momens, au plai-
<lb n="25.009"/>sir de les parcourir, &amp; de l'admirer; &amp;
<lb n="25.010"/>tout de suite ils étoient rappellés, par
<lb n="25.011"/>celui bien plus doux, de contempler
<lb n="25.012"/>le grand homme devant qui j'étois. Son
<lb n="25.013"/>air étoit sec &amp; austère, &amp; son sourire
<lb n="25.014"/>malin, mais il avoit une noblesse infinie
<lb n="25.015"/>dans ses plus petits mouvemens. Après
<lb n="25.016"/>quelques complimens mal rangés, qu'ap-
<lb n="25.017"/>paremment je ne lui débitai pas de meil-
<lb n="25.018"/>leure grace, car le respect dont je fus
<lb n="25.019"/>saisi en le voyant m'avoit interdit; il
<lb n="25.020"/>me demanda poliment, par quel hazard
<lb n="25.021"/>je me trouvois-là? Je ne puis vous l'ap-
<lb n="25.022"/>prendre, lui dis-je, puisque je l'ignore
<lb n="25.023"/>moi-même. Je me suis trouvé, sans sça-
<lb n="25.024"/>voir, ni pourquoi, ni comment, de-
<lb n="25.025"/>vant la porte de ce Palais, j'en parcours
<lb n="25.026"/>les différens appartemens depuis quel-
<pb n="26"/>
<fw>(18)</fw>
<lb n="26.001"/>ques heures, sans rameau d'or &amp; sans
<lb n="26.002"/>sybile, &amp; autant que je suis réjoui
<lb n="26.003"/>de vous voir, autant j'ai le cœur flétri
<lb n="26.004"/>de ce que j'ai vû au Vestibule. Y avez-
<lb n="26.005"/>vous trouvé quelqu'un de votre con-
<lb n="26.006"/>noissance, me dit-il? Les étiquettes
<lb n="26.007"/>m'ont fait faire la découverte de plu-
<lb n="26.008"/>sieurs. Quelle différence, ô Dieux! de
<lb n="26.009"/>leur état présent, à ces mines discrettes
<lb n="26.010"/>&amp; ce maintien jaloux qui vous les fai-
<lb n="26.011"/>soit reconnoître Poëtes * là-haut! Ils
<lb n="26.012"/>se cachoient de honte, &amp; je n'en avois
<lb n="26.013"/>pas moins de la leur causer. Ils vous au-
<lb n="26.014"/>ront prié, sans doute, de rendre public
<lb n="26.015"/>leur sort, mais je suis bien sûr que leur
<lb n="26.016"/>état n'effrayera personne: J'eus beau
<lb n="26.017"/>couvrir d'opprobre &amp; de ridicule les
<lb n="26.018"/>Auteurs de mon tems, je ne pûs en con-
<lb n="26.019"/>tenir aucun. La race des Pelletiers &amp;
<lb n="26.020"/>des Cottins ne s'éteindra jamais, elle
<lb n="26.021"/>nous donnera au contraire une postérité
<lb n="26.022"/>plus vicieuse. Ce que vous dites là, re-
<lb n="26.023"/>pris-je, m'ôte beaucoup de regrets;
<lb n="26.024"/>je m'imaginois que s'il existoit un hom-
<lb n="26.025"/>me comme vous, dont les talens &amp; le
<lb n="26.026"/>goût fussent reconnus, &amp; qui fut jus-
<lb n="26.027"/><seg rend ="footnotes"/>
<lb n="26.028"/><p>  <seg rend = "small">{5*} Qu'à sa mine discrete &amp; son maintien ja-
<lb n="26.029"/>loux, je reconnus Poëte Satirique.</seg></p>
<pb n="27"/>
<fw>(19)</fw>
<lb n="27.001"/>te, vrai, &amp; inexorable dans sa critique;{??}
<lb n="27.002"/>ce seroit un frein qui réprimeroit la fu-
<lb n="27.003"/>reur qu'on a d'écrire, &amp; je faisois au
<lb n="27.004"/>Ciel les veux les plus ardens, pour qu'il
<lb n="27.005"/>nous l'accordât; mais ce que vous nous
<lb n="27.006"/>racontez du peu de succès que vous
<lb n="27.007"/>avez eu, me persuade que vous en au-
<lb n="27.008"/>riez bien moins à présent, que le mal
<lb n="27.009"/>n'a fait que s'accroître, &amp; que tant de
<lb n="27.010"/>gens sont siflés, que ce n'est plus une
<lb n="27.011"/>honte de l'être.</p>
<lb n="27.012"/><p>  Mais quoi, dit-il, les belles-lettres
<lb n="27.013"/>sont-elles dans une anarchie si générale,
<lb n="27.014"/>que personne n'y donne le ton? N'y
<lb n="27.015"/>a-t-il point d'Ecrivain habile &amp; zèlé
<lb n="27.016"/>qui veuille se charger d'éclairer le pu-
<lb n="27.017"/>blic, &amp; de le diriger vers le bon &amp; le
<lb n="27.018"/>beau? Ah! lui répondis-je vivement,
<lb n="27.019"/>c'est l'espèce la plus commune, &amp; qui-
<lb n="27.020"/>conque voudroit lire toutes les déci-
<lb n="27.021"/>sions de leur Parnasse, n'auroit pas d'au-
<lb n="27.022"/>tre lecture à faire. On doit cette justice
<lb n="27.023"/>à quelques-uns; qu'ils auroient les ta-
<lb n="27.024"/>lens nécessaires pour bien juger, s'ils
<lb n="27.025"/>avoient la sagesse de se renfermer dans
<lb n="27.026"/>leur ressort; mais ils ont la frenésie de
<lb n="27.027"/>vouloir l'étendre sur toute sorte de ma-
<lb n="27.028"/>tière; imaginés les décisions qui doivent
<lb n="27.029"/>émaner de Tribunaux aussi incompétens.
<pb n="28"/>
<fw>(20)</fw>
<lb n="28.001"/>Il est d'ailleurs impossible que tant de
<lb n="28.002"/>Juges différens ne rendent des Arrêts
<lb n="28.003"/>qui se contredisent, l'un exalte ce que
<lb n="28.004"/>l'autre avilit. Les cabales, les intri-
<lb n="28.005"/>gues, lapolitique &amp; l'intérêt, inspirent
<lb n="28.006"/>trop souvent ces Oracles de la Littéra-
<lb n="28.007"/>ture, &amp; ces Aristarques se comportent
<lb n="28.008"/>trop en Zoiles. Les Auteurs trouvant
<lb n="28.009"/>ainsi à se consoler des mépris des uns
<lb n="28.010"/>par les louanges des autres, continuent
<lb n="28.011"/>sur le même ton, &amp; le public se trouve
<lb n="28.012"/>par conséquent bien moins instruit &amp;
<lb n="28.013"/>éclairé, que s'il restoit abandonné à ses
<lb n="28.014"/>propres lumières.</p>
<lb n="28.015"/><p>  Ce que vous me racontez-là, me
<lb n="28.016"/>dit il, est étonnant, car s'il paroît tant
<lb n="28.017"/>d'ouvrages périodiques; à quelle pro-
<lb n="28.018"/>digieuse quantité ne doit pas monter
<lb n="28.019"/>ceux qui en fournissent la matière? Il
<lb n="28.020"/>n'est pas possible, lui dis-je, que vous
<lb n="28.021"/>puissiez imaginer les excès où l'on en est
<lb n="28.022"/>venu Les feuilles à la fin d'Octobre ne
<lb n="28.023"/>tombent pas si épaisses, que les brochu-
<lb n="28.024"/>res nouvelles, où, pour vous parler plus
<lb n="28.025"/>poëtiquement encore, comparez cha-
<lb n="28.026"/>que Libraire à un Dieu fleuve, dont
<lb n="28.027"/>la boutique est l'urne intarissable, d'où
<lb n="28.028"/>coulent sans cesse de grands flots, de
<lb n="28.029"/>contes, d'histoires, d'anecdotes, de
<pb n="29"/>
<fw>(21)</fw>
<lb n="29.001"/>nouvelles, de mémoires, d'avantures,
<lb n="29.002"/>de voyages &amp; autres fadeurs sous toute
<lb n="29.003"/>espèces de titres ridicules qui inondent
<lb n="29.004"/>le public.</p>
<lb n="29.005"/><p>  Il faut donc, reprit-il, ou que la
<lb n="29.006"/>France, soit toute peuplée d'Auteurs,
<lb n="29.007"/>ou qu'ils soient aussi fertiles que des
<lb n="29.008"/><seg rend="italic">Scuderis.</seg> * Nous avons, lui répondis-je,
<lb n="29.009"/>l'un &amp; l'autre avantage. On publie cha-
<lb n="29.010"/>que année l'inventaire de nos richesses
<lb n="29.011"/>littéraires, ** il ne seroit pourtant pas
<lb n="29.012"/>facile de les calculer; car quoiqu'il ne
<lb n="29.013"/>contienne que les noms des écrivains
<lb n="29.014"/>vivans, &amp; les titres de leurs ouvrages,
<lb n="29.015"/>il forme déja un volume fort épais, que
<lb n="29.016"/>nous avons la gloire de voir grossir tous
<lb n="29.017"/>les ans &amp; qui parviendra bientôt à l'<seg rend="italic">in-</seg>
<lb n="29.018"/><seg rend="italic">folio.</seg> Cela n'est pas si surprenant qu'il
<lb n="29.019"/>vous le paroît: avant de mettre au jour
<lb n="29.020"/>un ouvrage, on lisoit autrefois les an-
<lb n="29.021"/>ciens, on étudioit la nature, on médi-
<lb n="29.022"/>toit long-tems son sujet pour s'en ren-
<lb n="29.023"/>dre maître; aujourd'hui l'on a suppri-
<lb n="29.024"/>mé toutes ces longueurs: les Diction-
<lb n="29.025"/><seg rend ="footnotes"/>
<lb n="29.026"/><p>  <seg rend = "small">{5*} Bienheureux Scuderi dont la fertile plume,</seg></p>
<lb n="29.027"/><seg rend = "small">Peut tous les mois sans peine enfanter un
<lb n="29.028"/>volume.</seg>
<lb n="29.029"/><p><seg rend = "small">{5*}{5*} La France Littéraire.</seg></p>
<pb n="30"/>
<fw>(22)</fw>
<lb n="30.001"/>naires, &amp; sur quelle matière n'en a-t-on
<lb n="30.002"/>pas fait, épargnent toutes ces peines
<lb n="30.003"/>&amp; sont les sources uniques &amp; abondan-
<lb n="30.004"/>tes où l'on puise: c'est sur la brochure
<lb n="30.005"/>en faveur qu'on dirige son plan, celles
<lb n="30.006"/>du mois ou de l'an fournissent le rem-
<lb n="30.007"/>plissage, ensorte qu'il est presque aussi
<lb n="30.008"/>aisé d'en faire une que de l'acheter
<lb n="30.009"/>quand elle est imprimée.</p>
<lb n="30.010"/><p>  Vous me jettez à présent, me dit-il,
<lb n="30.011"/>dans un autre embarras; comment, ex-
<lb n="30.012"/>cepté pour habiller le sucre &amp; la canel-
<lb n="30.013"/>le, * peut-on trouver à vendre tant de
<lb n="30.014"/>mauvais écrits? On n'est pas du bel
<lb n="30.015"/>air, lui répondis-je, si on n'a lû la nou-
<lb n="30.016"/>veauté du jour, le bel esprit est à la
<lb n="30.017"/>mode, &amp; vous connoissez l'empire de
<lb n="30.018"/>la mode sur nous; elle fait tout acheter,
<lb n="30.019"/>on n'imprime que des frivolités, &amp; à for-
<lb n="30.020"/>ce d'en lire, on en prend le goût au
<lb n="30.021"/>point, qu'il ne peut être affecté que
<lb n="30.022"/>par elles.</p>
<lb n="30.023"/><p>  Sçavez-vous, continuai-je, qu'on a
<lb n="30.024"/>trouvé le moyen de rendre les Contes
<lb n="30.025"/>de la Fontaine chastes? Ah! qu'elle est
<lb n="30.026"/>la main habile, dit-il, qui a pû jetter
<lb n="30.027"/><seg rend ="footnotes"/>
<lb n="30.028"/><p>  <seg rend = "small">{5*} Habiller chez Francœur, le sucre &amp; là{??}
<lb n="30.029"/>e{??}anelle.</seg></p>
<pb n="31"/>
<fw>(23)</fw>
<lb n="31.001"/>un voile sur ces nudités? La chose vous
<lb n="31.002"/>paroîtra d'autant plus surprenante, que
<lb n="31.003"/>plusieurs y ont travaillé; mais, lui-dis-
<lb n="31.004"/>je, nous l'entendons dans deux sens
<lb n="31.005"/>bien différens, je veux dire qu'on a fait
<lb n="31.006"/>des romans &amp; des contes si détestables,
<lb n="31.007"/>&amp; en si grand nombre, que les contes
<lb n="31.008"/>sont innocens en comparaison, &amp; par
<lb n="31.009"/>la familiarité qu'ils ont fait contracter
<lb n="31.010"/>avec les obscénités. Ceux de la Fontai-
<lb n="31.011"/>ne ne disent le fait qu'en gros, les au-
<lb n="31.012"/>tres le détaillent dans ses moindres cir-
<lb n="31.013"/>constances, &amp; en font des peintures si
<lb n="31.014"/>vives, qu'il n'est point de cœur qui
<lb n="31.015"/>puisse se sauver des impressions qu'elles
<lb n="31.016"/>font. Ces corrupteurs des mœurs, re-
<lb n="31.017"/>prit-il d'un ton échauffé, sont pires
<lb n="31.018"/>que des <seg rend="italic">Locustes,</seg> des <seg rend="italic">Brinvilliers</seg> &amp; des
<lb n="31.019"/><seg rend="italic">Voisins.</seg> Il y en a sur-tout quelques-uns,
<lb n="31.020"/>ajoûtai-je, qui sont d'autant plus cou-
<lb n="31.021"/>pables, qu'ils y ont prodigué tout l'es-
<lb n="31.022"/>prit possible.</p>
<lb n="31.023"/><p>  Ce récit l'avoit aigri, je m'en apper-
<lb n="31.024"/>çus &amp; je m'arrêtai. Quand il vit que je
<lb n="31.025"/>gardois le silence, il m'interrogea ainsi:
<lb n="31.026"/>la scène françoise est elle toujours en
<lb n="31.027"/>proie aux Pradons? Nous devons cette
<lb n="31.028"/>gloire à nos Auteurs vivans, lui dis je,
<lb n="31.029"/>que le théâtre a fait sous eux des pro-
<pb n="32"/>
<fw>(24)</fw>
<lb n="32.001"/>grès considérables. On ne travaille plus
<lb n="32.002"/>à présent dans le goût de votre tems,
<lb n="32.003"/>ce genre a vieilli &amp; a passé. Quoi, dit-
<lb n="32.004"/>il tout en feu, la manière dont Moliere,
<lb n="32.005"/>Corneille &amp; Racine ont traité la comé-
<lb n="32.006"/>die &amp; la tragédie, qu'ils avoient pres-
<lb n="32.007"/>que porté à leur perfection, n'est plus de
<lb n="32.008"/>mode? Je suis bien impatient de sçavoir
<lb n="32.009"/>quel est le genre nouveau qu'ils ont sub-
<lb n="32.010"/>stitué à l'ancien?</p>
<lb n="32.011"/><p>  La tragédie nouvelle brille en pom-
<lb n="32.012"/>peuses déclamations &amp; en fréquentes
<lb n="32.013"/>sentences; on n'y voit point, comme
<lb n="32.014"/>dans l'ancienne, les héros pleins de feu,
<lb n="32.015"/>&amp; de la passion qui les agite, en pour-
<lb n="32.016"/>suivre l'objet avec force &amp; sans relâche
<lb n="32.017"/>jusqu'à la fin, ils sont au contraire d'un
<lb n="32.018"/>froid &amp; d'une tranquillité admirable.
<lb n="32.019"/>Au lieu d'action, ils étalent la méta-
<lb n="32.020"/>physique la plus subtile, &amp; font la dis-
<lb n="32.021"/>section la plus fine des sentimens dont
<lb n="32.022"/>ils se disent animés. Ces sentimens au
<lb n="32.023"/>reste ne sont ni tels qu'ils devroient les
<lb n="32.024"/>avoir, ni tels qu'ils les ont eus, en quoi
<lb n="32.025"/>la supériorité de génie de nos tragiques
<lb n="32.026"/>est manifeste, car au lieu de piller dans
<lb n="32.027"/>la nature ou dans l'histoire, ils pren-
<lb n="32.028"/>nent dans leur esprit &amp; leur imagination.
<lb n="32.029"/>Il y a communément une ou plusieurs
<pb n="33"/>
<fw>(25)</fw>
<lb n="33.001"/>reconnoissances; ce qui fait, on ne scau-
<lb n="33.002"/>roit en disconvenir, des coups de théâ-
<lb n="33.003"/>tre des plus frappans &amp; des plus tou-
<lb n="33.004"/>chans. L'on voit du commencement du
<lb n="33.005"/>premier acte, le dénouement qui doit
<lb n="33.006"/>arriver au cinquième, malgré les obsta-
<lb n="33.007"/>cles qu'on accumule dans les autres pour
<lb n="33.008"/>pouvoir les remplir. C'est-là une très-
<lb n="33.009"/>grande découverte qu'on a faite, au
<lb n="33.010"/>moyen de laquelle on délivre les specta-
<lb n="33.011"/>teurs de cette agitation &amp; de cette in-
<lb n="33.012"/>quiétude qui les tenoit dans les allarmes
<lb n="33.013"/>&amp; la peine jusqu'à la fin. On leur a
<lb n="33.014"/>sauvé aussi cette émotion tendre ou
<lb n="33.015"/>terrible que font éprouver les piéces de
<lb n="33.016"/>Racine &amp; de Corneille. On est d'une
<lb n="33.017"/>tranquillité merveilleuse pendant tout
<lb n="33.018"/>le spectacle, &amp; l'on assiste le plus pai-
<lb n="33.019"/>siblement du monde au mariage des
<lb n="33.020"/>parties, qui s'ensuit d'ordinaire fort
<lb n="33.021"/>heureusement. On sort un peu ennuyé,
<lb n="33.022"/>mais fort content, &amp; on n'emporte
<lb n="33.023"/>point avec soi cette tristesse &amp; cette
<lb n="33.024"/>crainte dont on se laisse pénétrer aux
<lb n="33.025"/>piéces anciennes &amp; dont on a peine à se
<lb n="33.026"/>laisser distraire long-tems après.</p>
<lb n="33.027"/><p>  Le service que ces Auteurs rendent
<lb n="33.028"/>à la nation est essentiel. Ils ont craint
<lb n="33.029"/>que si on continuoit à faire des pièces
<pb n="34"/>
<fw>(26)</fw>
<lb n="34.001"/>qui excitassent des sentimens aussi tristes
<lb n="34.002"/>que la terreur &amp; la pitié; nous ne de-
<lb n="34.003"/>vinsions aussi sombres &amp; aussi mélanco-
<lb n="34.004"/>liques que des Anglois, vû le goût dé-
<lb n="34.005"/>cidé que l'on a pour le théâtre, &amp; que
<lb n="34.006"/>la gayeté nationale ne s'éteignit totale-
<lb n="34.007"/>ment, &amp; ils ont bien pourvû à ce mal-
<lb n="34.008"/>heur. D'un autre côté, le François
<lb n="34.009"/>étant porté à rire comme il l'est, il
<lb n="34.010"/>étoit également dangereux que si la
<lb n="34.011"/>comédie produisoit cet effet, nous ne
<lb n="34.012"/>devinssions trop légers &amp; trop badins;
<lb n="34.013"/>on l'a corrigée &amp; on l'a rendue toute
<lb n="34.014"/>sérieuse. Vous voilà en état d'admirer
<lb n="34.015"/>à présent le sage tempérament qu'ils ont
<lb n="34.016"/>trouvé en faisant des tragédies, où au
<lb n="34.017"/>lieu de verser des larmes, on rit quel-
<lb n="34.018"/>quefois; &amp; des comédies, où au lieu de
<lb n="34.019"/>rire, on larmoye. C'est ainsi que dans
<lb n="34.020"/>le siècle philosophe où nous vivons, on
<lb n="34.021"/>fait usage de ce grand principe: <seg rend="italic">Que le</seg>
<lb n="34.022"/><seg rend="italic">dramatique doit purger les passions</seg> {et} <seg rend="italic">cor-</seg>
<lb n="34.023"/><seg rend="italic">riger les mœurs.</seg></p>
<lb n="34.024"/><p>  On ne sçauroit nier que nos plaisirs
<lb n="34.025"/>n'ayent gagné à cette réforme &amp; qu'ils
<lb n="34.026"/>ne soient devenus plus décens. Etoit-il
<lb n="34.027"/>bienséant en effet, Monsieur, d'aller
<lb n="34.028"/>devant le monde, pleurer à chaudes
<lb n="34.029"/>larmes ou rire à gorge déployée? Cela
<lb n="34.030"/>n'est pardonnable qu'au peuple. On
<pb n="35"/>
<fw>(27)</fw>
<lb n="35.001"/>fait tout ce qu'on peut pour corriger
<lb n="35.002"/>les honnêtes gens, mais on n'en a pas
<lb n="35.003"/>encore trouvé le moyen, ils ont un
<lb n="35.004"/>penchant étonnant pour les pièces de
<lb n="35.005"/>votre tems, &amp; quoiqu'ils les ayent vûes
<lb n="35.006"/>un million de fois, elles ne manquent
<lb n="35.007"/>jamais de produire sur eux le même
<lb n="35.008"/>effet, mais on les en déshabitue si bien,
<lb n="35.009"/>qu'il faut espérer qu'on les fera changer.</p>
<lb n="35.010"/><p>  Quelle différence, Monsieur, entre
<lb n="35.011"/>cet ancien bas comique de Moliere, &amp;
<lb n="35.012"/>le haut comique d'aujourd'hui? On ne
<lb n="35.013"/>peut assister à l'un sans rire, au point
<lb n="35.014"/>qu'on en a honte soi-même; l'autre
<lb n="35.015"/>au contraire, noble &amp; grave, fait, à la
<lb n="35.016"/>vérité, bailler quelquefois, mais est
<lb n="35.017"/>rempli de moralités &amp; d'instructions.
<lb n="35.018"/>Dans l'un on voit un avare, un mysan-
<lb n="35.019"/>trope, soutenir tout uniment leur mê-
<lb n="35.020"/>me caractère jusqu'à la fin par leurs ac-
<lb n="35.021"/>tions; l'autre s'est affranchi de cet es-
<lb n="35.022"/>clavage: on ne fait plus l'intrigue pour
<lb n="35.023"/>le caractère, afin qu'en agissant, il se
<lb n="35.024"/>développe &amp; se fasse connoître; c'est
<lb n="35.025"/>le caractère qui est destiné sur l'intrigue
<lb n="35.026"/>&amp; qui se plie à tous ses besoins. Aussi
<lb n="35.027"/>au lieu de cette uniformité ancienne,
<lb n="35.028"/>cela produit une variété qui vous éton-
<lb n="35.029"/>neroit. Dans l'un le style est simple &amp;
<lb n="35.030"/>naturel; l'autre est sur le ton le plus
<pb n="36"/>
<fw>(28)</fw>
<lb n="36.001"/>élevé &amp; le plus précieux, &amp; tout jus-
<lb n="36.002"/>qu'à la plaisanterie y est d'un sérieux &amp;
<lb n="36.003"/>d'une dignité admirable.</p>
<lb n="36.004"/><p>  J'allois continuer, mais il m'interrom-
<lb n="36.005"/>pit brusquement: votre récit m'échauffe
<lb n="36.006"/>la bile au point que je n'y puis plus
<lb n="36.007"/>tenir. Suivez moi, me dit-il, allons
<lb n="36.008"/>joindre Corneille, Racine &amp; Moliere,
<lb n="36.009"/>qui se promenent dans les jardins, vous
<lb n="36.010"/>leur ferez tout ce beau détail; au re-
<lb n="36.011"/>tour vous visiterez nos appartemens. Il
<lb n="36.012"/>y en a non-{??}seulement pour les morts;
<lb n="36.013"/>vous verrez encore ceux qui sont desti-
<lb n="36.014"/>nés aux Auteurs vivans. Les beautés
<lb n="36.015"/>qu'ils mettent dans leurs écrits se con-
<lb n="36.016"/>vertissent, à mesure qu'ils les mettent au
<lb n="36.017"/>jour, en autant d'ornemens qui les em-
<lb n="36.018"/>bellissent. Il y en a pour Voltaire, pour
<lb n="36.019"/>Crebillon, Gresset, le Franc, &amp;c. Et
<lb n="36.020"/>par ce que je vous dis vous pouvez ju-
<lb n="36.021"/>ger de leur magnificence; mais les im-
<lb n="36.022"/>perfections y passent également, &amp; les
<lb n="36.023"/>ternissent &amp; les dégradent. Vous vous
<lb n="36.024"/>appercevrez que le mien se ressent de
<lb n="36.025"/>l'équivoque &amp; de plusieurs de mes saty-
<lb n="36.026"/>res. Qu'ils ne succombent donc pas à
<lb n="36.027"/>la foiblesse de donner de ces éditions si
<lb n="36.028"/>complettes, où avec les chefs{??}-d'œuvres
<lb n="36.029"/>de leurs veilles, on trouve les rêves de
<lb n="36.030"/>leur sommeil.</p>
<pb n="37"/>
<fw>(29)</fw>
<lb n="37.001"/><p>  Nous marchions à grands pas tandis
<lb n="37.002"/>qu'il me parloit ainsi, &amp; nous traver-
<lb n="37.003"/>sions les lieux du monde les plus beaux.
<lb n="37.004"/>J'étois enchanté &amp; ravi; je n'en entre-
<lb n="37.005"/>prendrai pas la description; ce que Vir-
<lb n="37.006"/>gile a dit des Elisées, Milton du Jardin
<lb n="37.007"/>d'Eden, pourroit à peine en donner une
<lb n="37.008"/>idée. C'est ici, me dit mon Con-
<lb n="37.009"/>ducteur, un parc immense, autour du-
<lb n="37.010"/>quel sont rangés les palais des Auteurs
<lb n="37.011"/>des différentes Nations Il est commun
<lb n="37.012"/>à toutes, &amp; chacune y a ses jardins par-
<lb n="37.013"/>ticuliers. Voyez vous, me dit-il, sur
<lb n="37.014"/>votre droite ces bois si mal élagués &amp; si
<lb n="37.015"/>touffus, où il y a tant d'arbres si verds
<lb n="37.016"/>&amp; dont la tête s'élève si haut; &amp; où il
<lb n="37.017"/>y en a tant d'autres si pâles &amp; dont les
<lb n="37.018"/>rameaux pendent si près de terre. Voyez-
<lb n="37.019"/>vous ces allées si magnifiques, &amp; si irré-
<lb n="37.020"/>gulières, ces jets d'eau si abondans &amp; si
<lb n="37.021"/>élevés, &amp; ces eaux si plattes &amp; si basses:
<lb n="37.022"/>c'est le quartier des Anglois. Tournez-
<lb n="37.023"/>vous sur votre gauche, remarquez ces
<lb n="37.024"/>palissades si charmantes, ces bosquets si
<lb n="37.025"/>rians, ces parterres si ornés où les fleurs
<lb n="37.026"/>recherchées sont en si grande profusion:
<lb n="37.027"/>c'est celui des Italiens. Mais voici devant
<lb n="37.028"/>nous ceux que nous cherchons, ils sont
<lb n="37.029"/>en bonne compagnie, Homere, Sopho-
<pb n="38"/>
<fw>(30)</fw>
<lb n="38.001"/>cle, Euripide, Virgile &amp; Horace sont
<lb n="38.002"/>avec eux. A ces mots le cœur me bat-
<lb n="38.003"/>tit vivement, nous les joignimes dans
<lb n="38.004"/>un instant &amp; je leur fis la révérence la
<lb n="38.005"/>plus respectueuse: j'étois tout stupéfait
<lb n="38.006"/>du plaisir de les voir, &amp; tandis que mon
<lb n="38.007"/>Guide leur répétoit avec l'ironie la plus
<lb n="38.008"/>amère, ce que je venois de lui dire, je
<lb n="38.009"/>m'occupois à le contempler. Je ne pou-
<lb n="38.010"/>vois, sur-tout, me lasser d'admirer Ho-
<lb n="38.011"/>mere &amp; Virgile, ces Patriarches de la
<lb n="38.012"/>belle Littérature, au lieu de cette figu-
<lb n="38.013"/>re antique &amp; de médaille que je leur
<lb n="38.014"/>supposois, la jeunesse la plus fraîche &amp;
<lb n="38.015"/>la plus vigoureuse, les graces les plus
<lb n="38.016"/>aimables, l'air le plus noble &amp; le plus
<lb n="38.017"/>majestueux brilloient dans toute leur
<lb n="38.018"/>personne; je me sentois pour eux le res-
<lb n="38.019"/>pect &amp; l'amour les plus vifs. Je me prépa-
<lb n="38.020"/>rois à goûter le charme délicieux d'une
<lb n="38.021"/>conversation avec de tels hommes, lors-
<lb n="38.022"/>qu'à force de saignées &amp; d'émétique,
<lb n="38.023"/>mon ame fut rappellée à la vie, <seg rend="italic">ou plutôt</seg>
<lb n="38.024"/><seg rend="italic">aux douleurs,</seg> par le fil délié qui l'y re-
<lb n="38.025"/>tenoit encore. A peine ai-je été rétabli
<lb n="38.026"/>que je me suis empressé de donner la Re-
<lb n="38.027"/>lation de mon voyage, &amp; de m'acquit-
<lb n="38.028"/>ter des différentes commissions qu'on
<lb n="38.029"/>m'a données.</p>
<lb n="38.030"/><head>FIN.</head></body>
</text>